target_terminusdb
